resume_as_code/__init__.py
resume_as_code/__main__.py
resume_as_code/__version__.py
resume_as_code/cli.py
resume_as_code/config.py
resume_as_code/context.py
resume_as_code/data_loader.py
resume_as_code/py.typed
resume_as_code/commands/__init__.py
resume_as_code/commands/build.py
resume_as_code/commands/cache.py
resume_as_code/commands/config_cmd.py
resume_as_code/commands/infer.py
resume_as_code/commands/init.py
resume_as_code/commands/list_cmd.py
resume_as_code/commands/migrate.py
resume_as_code/commands/new.py
resume_as_code/commands/plan.py
resume_as_code/commands/remove.py
resume_as_code/commands/show.py
resume_as_code/commands/test_errors.py
resume_as_code/commands/test_output.py
resume_as_code/commands/validate.py
resume_as_code/data/__init__.py
resume_as_code/data/skills.yaml
resume_as_code/data/archetypes/__init__.py
resume_as_code/data/archetypes/cultural.yaml
resume_as_code/data/archetypes/greenfield.yaml
resume_as_code/data/archetypes/incident.yaml
resume_as_code/data/archetypes/leadership.yaml
resume_as_code/data/archetypes/migration.yaml
resume_as_code/data/archetypes/minimal.yaml
resume_as_code/data/archetypes/optimization.yaml
resume_as_code/data/archetypes/strategic.yaml
resume_as_code/data/archetypes/transformation.yaml
resume_as_code/migrations/__init__.py
resume_as_code/migrations/backup.py
resume_as_code/migrations/base.py
resume_as_code/migrations/registry.py
resume_as_code/migrations/v1_to_v2.py
resume_as_code/migrations/v2_to_v3.py
resume_as_code/migrations/v3_to_v4.py
resume_as_code/migrations/yaml_handler.py
resume_as_code/models/__init__.py
resume_as_code/models/board_role.py
resume_as_code/models/certification.py
resume_as_code/models/config.py
resume_as_code/models/education.py
resume_as_code/models/embeddings.py
resume_as_code/models/errors.py
resume_as_code/models/exclusion.py
resume_as_code/models/job_description.py
resume_as_code/models/manifest.py
resume_as_code/models/output.py
resume_as_code/models/plan.py
resume_as_code_ng-2.0.2.dist-info/METADATA
resume_as_code_ng-2.0.2.dist-info/WHEEL
resume_as_code_ng-2.0.2.dist-info/entry_points.txt
resume_as_code_ng-2.0.2.dist-info/licenses/LICENSE
resume_as_code_ng-2.0.2.dist-info/RECORD
