Metadata-Version: 2.4
Name: resume-as-code-ng
Version: 2.0.2
Summary: CLI tool for git-native resume generation from structured work units
Project-URL: Homepage, https://github.com/drbothen/resume-as-code
Project-URL: Documentation, https://drbothen.github.io/resume-as-code/
Project-URL: Repository, https://github.com/drbothen/resume-as-code
Project-URL: Issues, https://github.com/drbothen/resume-as-code/issues
Project-URL: Changelog, https://github.com/drbothen/resume-as-code/releases
Author-email: Joshua Magady <josh.magady@gmail.com>
License: MIT
License-File: LICENSE
Keywords: career,cli,cv,docx,git,job-description,job-search,pdf,resume,yaml
Classifier: Development Status :: 4 - Beta
Classifier: Environment :: Console
Classifier: Intended Audience :: Developers
Classifier: Intended Audience :: End Users/Desktop
Classifier: License :: OSI Approved :: MIT License
Classifier: Operating System :: OS Independent
Classifier: Programming Language :: Python :: 3
Classifier: Programming Language :: Python :: 3.10
Classifier: Programming Language :: Python :: 3.11
Classifier: Programming Language :: Python :: 3.12
Classifier: Programming Language :: Python :: 3.13
Classifier: Topic :: Office/Business
Classifier: Topic :: Text Processing :: Markup
Classifier: Topic :: Utilities
Classifier: Typing :: Typed
Requires-Python: >=3.10
Requires-Dist: click>=8.1
Requires-Dist: docxtpl>=0.16
Requires-Dist: httpx>=0.27
Requires-Dist: jinja2>=3.1
Requires-Dist: jsonschema>=4.20
Requires-Dist: pydantic>=2.0
Requires-Dist: python-docx>=1.1
Requires-Dist: pyyaml>=6.0
Requires-Dist: rank-bm25>=0.2
Requires-Dist: rich>=13
Requires-Dist: ruamel-yaml>=0.18
Requires-Dist: sentence-transformers>=2.2
Requires-Dist: weasyprint>=68
Provides-Extra: dev
Requires-Dist: mypy; extra == 'dev'
Requires-Dist: pre-commit; extra == 'dev'
Requires-Dist: pytest-cov; extra == 'dev'
Requires-Dist: pytest>=8.0; extra == 'dev'
Requires-Dist: respx>=0.21.1; extra == 'dev'
Requires-Dist: ruff; extra == 'dev'
Provides-Extra: llm
Requires-Dist: anthropic>=0.25; extra == 'llm'
Requires-Dist: openai>=1.0; extra == 'llm'
Provides-Extra: nlp
Requires-Dist: spacy>=3.7; extra == 'nlp'
